pipeworker/__init__.py
pipeworker/__version__.py
pipeworker/config.py
pipeworker/utils.py
pipeworker/base/Block.py
pipeworker/base/BlockGroup.py
pipeworker/base/Parallel.py
pipeworker/base/Pipeline.py
pipeworker/base/Sequence.py
pipeworker/base/__init__.py
pipeworker/blocks/Data.py
pipeworker/blocks/Filter.py
pipeworker/blocks/Function.py
pipeworker/blocks/Map.py
pipeworker/blocks/Merge.py
pipeworker/blocks/__init__.py
pipeworker/blocks/cache/CacheMissException.py
pipeworker/blocks/cache/CachedBlock.py
pipeworker/blocks/cache/FileCache.py
pipeworker/blocks/cache/__init__.py
pipeworker/blocks/datasets/CompareMeasurementAndPrint.py
pipeworker/blocks/datasets/Measure.py
pipeworker/blocks/datasets/PlotResults.py
pipeworker/blocks/datasets/PrintMeasurements.py
pipeworker/blocks/datasets/TrainTestSplit.py
pipeworker/blocks/datasets/__init__.py
pipeworker/functions/__init__.py
pipeworker/functions/measurements.py
pipeworker/functions/utils.py
pipeworker/loggers/Logger.py
pipeworker/loggers/__init__.py
pipeworker/types/Dataset.py
pipeworker/types/Invokable.py
pipeworker/types/Mergable.py
pipeworker/types/TrainAndTestDataset.py
pipeworker/types/__init__.py
tests/blocks/FilterBlockTest.py
tests/blocks/MapBlockTest.py
tests/blocks/MergeBlockTest.py
tests/blocks/__init__.py
tests/blocks/cache/CachedBlockTest.py
tests/blocks/cache/FileCacheTest.py
tests/blocks/cache/FileCacheWithoutPathTest.py
tests/blocks/cache/__init__.py
tests/blocks/datasets/CompareMeasurementAndPrintTest.py
tests/blocks/datasets/MeasureTest.py
tests/blocks/datasets/TrainTestSplitTest.py
tests/blocks/datasets/__init__.py
tests/blocks/functions/MeasurementsTest.py
tests/blocks/functions/UtilsTest.py
tests/blocks/functions/__init__.py
tests/types/DatasetTest.py
tests/types/__init__.py
pipeworker-0.1.7.dist-info/LICENSE
pipeworker-0.1.7.dist-info/METADATA
pipeworker-0.1.7.dist-info/WHEEL
pipeworker-0.1.7.dist-info/top_level.txt
pipeworker-0.1.7.dist-info/RECORD
